setup.py
dportscanner/__init__.py
dportscanner/scan.py
dportscanner.egg-info/PKG-INFO
dportscanner.egg-info/SOURCES.txt
dportscanner.egg-info/dependency_links.txt
dportscanner.egg-info/requires.txt
dportscanner.egg-info/top_level.txt
dportscanner/mylib/__init__.py
dportscanner/mylib/address.py
dportscanner/mylib/mapper.py
dportscanner/mylib/toplevel.py