Metadata-Version: 1.0
Name: dportscanner
Version: 1.3
Summary: Custom port scanner 
Home-page: https://github.com/daviddexter/dportscanner
Author: David Dexter www.blackspace.co.ke
Author-email: dmwangimail@gmail.com
License: GPL v3 or any later version
Keywords: port,scanner
Platform: UNKNOWN
